CHANGELOG.rst
CONTRIBUTING.rst
MANIFEST.in
MIT-license.txt
Makefile
README.rst
ROADMAP.rst
helpfile.txt
qtop
qtop.py
qtopconf.yaml
setup.py
qtop.egg-info/PKG-INFO
qtop.egg-info/SOURCES.txt
qtop.egg-info/dependency_links.txt
qtop.egg-info/top_level.txt
qtop_py/__init__.py
qtop_py/colormap.py
qtop_py/constants.py
qtop_py/fileutils.py
qtop_py/serialiser.py
qtop_py/utils.py
qtop_py/web.py
qtop_py/yaml_parser.py
qtop_py/../qtop.py
qtop_py/../qtopconf.yaml
qtop_py/contrib/func_tests.sh
qtop_py/contrib/oar1_dvv_out.ref
qtop_py/contrib/oarnodes_Y.txt
qtop_py/contrib/oarnodes_s_Y.txt
qtop_py/contrib/oarstat.txt
qtop_py/contrib/pbs_dvv_out.ref
qtop_py/contrib/pbsnodes_a.txt
qtop_py/contrib/qstat.F.xml.stdout
qtop_py/contrib/qstat.txt
qtop_py/contrib/qstat_q.txt
qtop_py/contrib/qtop_demo.gif
qtop_py/contrib/sger_dvv_out.ref
qtop_py/inputs/joboutputs.sh
qtop_py/inputs/jobstatuses.sh
qtop_py/inputs/jobsubmits.sh
qtop_py/inputs/qtop-input.jdl
qtop_py/inputs/qtop-input.sh
qtop_py/legacy/__init__.py
qtop_py/legacy/counter.py
qtop_py/legacy/namedtuple.py
qtop_py/legacy/ordereddict.py
qtop_py/plugins/__init__.py
qtop_py/plugins/demo.py
qtop_py/plugins/oar.py
qtop_py/plugins/pbs.py
qtop_py/plugins/sge.py
qtop_py/ui/__init__.py
qtop_py/ui/viewport.py
qtop_py/web/index.html
tests/test_qtop.py
tests/test_yaml_parser.py
tests/plugins/__init__.py
tests/plugins/test_pbs.py
tests/ui/__init__.py
tests/ui/test_viewport.py