Metadata-Version: 1.0
Name: qtop
Version: 0.9.20161216
Summary: qtop: the fast text mode way to monitor your cluster's utilization and status;
Home-page: https://github.com/qtop/qtop
Author: Sotiris Fragkiskos
Author-email: sfranky@gmail.com
License: MIT
Platform: UNKNOWN
